README.md
django_a2a/__init__.py
django_a2a/admin.py
django_a2a/apps.py
django_a2a/views.py
django_a2a/migrations/0001_initial.py
django_a2a/migrations/__init__.py
django_a2a/models/__init__.py
django_a2a/models/artifact.py
django_a2a/models/message.py
django_a2a/models/part.py
django_a2a/models/task.py
django_a2a/serializers/artifact.py
django_a2a/serializers/message.py
django_a2a/serializers/part.py
django_a2a/serializers/task.py
django_a2a/tests/__init__.py
django_a2a/tests/test_artifact_model.py
django_a2a/tests/test_artifact_part_model.py
django_a2a/tests/test_artifact_serializer.py
django_a2a/tests/test_message_model.py
django_a2a/tests/test_message_part_model.py
django_a2a/tests/test_message_serializer.py
django_a2a/tests/test_part_serializer.py
django_a2a/tests/test_task_model.py
django_a2a/tests/test_task_serializer.py
django_a2a-0.1.1.dist-info/METADATA
django_a2a-0.1.1.dist-info/WHEEL
django_a2a-0.1.1.dist-info/licenses/LICENSE
django_a2a-0.1.1.dist-info/RECORD
